{"states_named":[{"icao24":"8a094a","callsign":"SJV964","origin_country":"PK-SJL","longitude":101.335749,"latitude":-0.018494,"baro_altitude":9144,"geo_altitude":9776,"on_ground":false,"velocity":233.2,"true_track":315.45,"vertical_rate":0,"squawk":"3357","aircraft_type":"A320","aircraft_desc":"AIRBUS A-320","registration":"PK-SJL"},{"icao24":"7504a1","callsign":"AXM349","origin_country":"9M-RAN","longitude":101.681353,"latitude":0.288528,"baro_altitude":11582,"geo_altitude":12360,"on_ground":false,"velocity":235,"true_track":299.65,"vertical_rate":0,"squawk":"6660","aircraft_type":"A320","aircraft_desc":"AIRBUS A-320","registration":"9M-RAN"},{"icao24":"8a081f","callsign":"LNI989","origin_country":"PK-LQZ","longitude":101.771472,"latitude":0.770579,"baro_altitude":8542,"geo_altitude":9106,"on_ground":false,"velocity":230.9,"true_track":289.53,"vertical_rate":0.33,"squawk":"2467","aircraft_type":"B738","aircraft_desc":"BOEING 737-800","registration":"PK-LQZ"},{"icao24":"8a0261","callsign":"LNI213","origin_country":"PK-LHO","longitude":102.151531,"latitude":0.692001,"baro_altitude":10058,"geo_altitude":10752,"on_ground":false,"velocity":230,"true_track":141.54,"vertical_rate":-0.16,"squawk":"4754","aircraft_type":"B739","aircraft_desc":"BOEING 737-900","registration":"PK-LHO"},{"icao24":"76b445","callsign":"SIA534","origin_country":"9V-MBE","longitude":102.809453,"latitude":1.796951,"baro_altitude":7597,"geo_altitude":8108,"on_ground":false,"velocity":226.9,"true_track":270.78,"vertical_rate":3.9,"squawk":"0131","aircraft_type":"B38M","aircraft_desc":"BOEING 737 MAX 8","registration":"9V-MBE"},{"icao24":"801828","callsign":"IGO1003","origin_country":"VT-IXT","longitude":102.912427,"latitude":1.659164,"baro_altitude":8900,"geo_altitude":9510,"on_ground":false,"velocity":220.3,"true_track":101.99,"vertical_rate":-5.2,"squawk":"0620","aircraft_type":"A20N","aircraft_desc":"AIRBUS A-320neo","registration":"VT-IXT"},{"icao24":"8a07ce","callsign":"BTK6887","origin_country":"PK-BDF","longitude":103.067865,"latitude":-0.491776,"baro_altitude":10668,"geo_altitude":11400,"on_ground":false,"velocity":233.8,"true_track":143.23,"vertical_rate":0,"squawk":"4742","aircraft_type":"A20N","aircraft_desc":"AIRBUS A-320neo","registration":"PK-BDF"},{"icao24":"8a04a5","callsign":"CTV503","origin_country":"PK-GQA","longitude":103.238898,"latitude":1.129074,"baro_altitude":9388,"geo_altitude":10028,"on_ground":false,"velocity":235.7,"true_track":151.59,"vertical_rate":4.06,"squawk":"2160","aircraft_type":"A320","aircraft_desc":"AIRBUS A-320","registration":"PK-GQA"},{"icao24":"8a0927","callsign":"PAS357","origin_country":"PK-PWD","longitude":103.31543,"latitude":-2.098761,"baro_altitude":11285,"geo_altitude":null,"on_ground":false,"velocity":226.4,"true_track":281.2,"vertical_rate":-0.01,"squawk":"6256","aircraft_type":"A320","aircraft_desc":"AIRBUS A-320","registration":"PK-PWD"},{"icao24":"8a06f0","callsign":"AWQ556","origin_country":"PK-AZK","longitude":103.741709,"latitude":1.402496,"baro_altitude":11590,"geo_altitude":12352,"on_ground":false,"velocity":233.5,"true_track":307.93,"vertical_rate":0.33,"squawk":"4110","aircraft_type":"A320","aircraft_desc":"AIRBUS A-320","registration":"PK-AZK"},{"icao24":"8a0a8a","callsign":"PAS325","origin_country":"","longitude":103.798691,"latitude":-1.645569,"baro_altitude":10676,"geo_altitude":null,"on_ground":false,"velocity":228.9,"true_track":137.4,"vertical_rate":-0.01,"squawk":"6226","aircraft_type":null,"aircraft_desc":null,"registration":null},{"icao24":"76cd12","callsign":"SIA510","origin_country":"9V-SHR","longitude":103.809104,"latitude":1.713309,"baro_altitude":3863,"geo_altitude":4100,"on_ground":false,"velocity":199.1,"true_track":316.78,"vertical_rate":6.5,"squawk":"0175","aircraft_type":"A359","aircraft_desc":"AIRBUS A-350-900","registration":"9V-SHR"},{"icao24":"76cda2","callsign":"SIA431","origin_country":"9V-SMB","longitude":103.834581,"latitude":1.117859,"baro_altitude":1090,"geo_altitude":1151,"on_ground":false,"velocity":102,"true_track":52.38,"vertical_rate":-2.6,"squawk":"7462","aircraft_type":"A359","aircraft_desc":"AIRBUS A-350-900","registration":"9V-SMB"},{"icao24":"750571","callsign":"MXD805","origin_country":"9M-LDP","longitude":103.900783,"latitude":1.181775,"baro_altitude":922,"geo_altitude":983,"on_ground":false,"velocity":102.2,"true_track":51.75,"vertical_rate":-1.95,"squawk":"2173","aircraft_type":"B738","aircraft_desc":"BOEING 737-800","registration":"9M-LDP"},{"icao24":"75021f","callsign":"MAS722","origin_country":"9M-MXU","longitude":103.919536,"latitude":0.698377,"baro_altitude":10363,"geo_altitude":11087,"on_ground":false,"velocity":246.5,"true_track":345.12,"vertical_rate":null,"squawk":null,"aircraft_type":"B738","aircraft_desc":"BOEING 737-800","registration":"9M-MXU"},{"icao24":"7c7802","callsign":"QFA47","origin_country":"VH-XZO","longitude":103.948121,"latitude":1.0009,"baro_altitude":1989,"geo_altitude":2118,"on_ground":false,"velocity":95.2,"true_track":271.86,"vertical_rate":-2.44,"squawk":"1114","aircraft_type":"B738","aircraft_desc":"BOEING 737-800","registration":"VH-XZO"},{"icao24":"750467","callsign":"AXM721","origin_country":"9M-AGU","longitude":103.948706,"latitude":1.281024,"baro_altitude":457,"geo_altitude":488,"on_ground":false,"velocity":78.1,"true_track":22.85,"vertical_rate":-4.23,"squawk":"2136","aircraft_type":"A320","aircraft_desc":"AIRBUS A-320","registration":"9M-AGU"},{"icao24":"750591","callsign":"MAS124","origin_country":"9M-MVM","longitude":103.979544,"latitude":0.501114,"baro_altitude":10973,"geo_altitude":11735,"on_ground":false,"velocity":239,"true_track":344.65,"vertical_rate":0,"squawk":"1335","aircraft_type":"B38M","aircraft_desc":"BOEING 737 MAX 8","registration":"9M-MVM"},{"icao24":"76d106","callsign":"TGW695","origin_country":"9V-THF","longitude":104.017624,"latitude":2.574417,"baro_altitude":6607,"geo_altitude":7041,"on_ground":false,"velocity":197.5,"true_track":147.55,"vertical_rate":-8.78,"squawk":"0751","aircraft_type":"E290","aircraft_desc":"EMBRAER ERJ-190-300","registration":"9V-THF"},{"icao24":"76b44c","callsign":"SIA818","origin_country":"9V-MBL","longitude":104.018787,"latitude":1.406616,"baro_altitude":602,"geo_altitude":640,"on_ground":false,"velocity":111.3,"true_track":23.13,"vertical_rate":5.2,"squawk":"0115","aircraft_type":"B38M","aircraft_desc":"BOEING 737 MAX 8","registration":"9V-MBL"},{"icao24":"406f78","callsign":"BAW16","origin_country":"G-ZBKL","longitude":104.027912,"latitude":1.001724,"baro_altitude":1737,"geo_altitude":1844,"on_ground":false,"velocity":99.8,"true_track":271.18,"vertical_rate":-3.09,"squawk":"1373","aircraft_type":"B789","aircraft_desc":"BOEING 787-9 Dreamliner","registration":"G-ZBKL"},{"icao24":"76b442","callsign":"SIA735","origin_country":"9V-MBB","longitude":104.139497,"latitude":1.504486,"baro_altitude":3635,"geo_altitude":3871,"on_ground":false,"velocity":133,"true_track":190.7,"vertical_rate":-3.9,"squawk":"0756","aircraft_type":"B38M","aircraft_desc":"BOEING 737 MAX 8","registration":"9V-MBB"},{"icao24":"8832cf","callsign":"TLM104","origin_country":"HS-LVO","longitude":104.193815,"latitude":1.732162,"baro_altitude":3490,"geo_altitude":3703,"on_ground":false,"velocity":156.3,"true_track":193.12,"vertical_rate":-4.55,"squawk":"6110","aircraft_type":"B739","aircraft_desc":"BOEING 737-900","registration":"HS-LVO"},{"icao24":"7801b6","callsign":"CPA711","origin_country":"B-HLW","longitude":104.237862,"latitude":1.805695,"baro_altitude":3901,"geo_altitude":4161,"on_ground":false,"velocity":160.6,"true_track":197.33,"vertical_rate":-6.18,"squawk":"5310","aircraft_type":"A333","aircraft_desc":"AIRBUS A-330-300","registration":"B-HLW"},{"icao24":"7c4927","callsign":"QFA1","origin_country":"VH-OQH","longitude":104.346096,"latitude":1.157501,"baro_altitude":2819,"geo_altitude":3010,"on_ground":false,"velocity":147.7,"true_track":265,"vertical_rate":-4.55,"squawk":"1422","aircraft_type":"A388","aircraft_desc":"AIRBUS A-380-800","registration":"VH-OQH"},{"icao24":"7c1473","callsign":"QFA36","origin_country":"VH-EBP","longitude":104.357663,"latitude":0.674868,"baro_altitude":5936,"geo_altitude":6332,"on_ground":false,"velocity":200,"true_track":125.37,"vertical_rate":9.1,"squawk":"0122","aircraft_type":"A332","aircraft_desc":"AIRBUS A-330-200","registration":"VH-EBP"},{"icao24":"76b86c","callsign":"TGW517","origin_country":"9V-NCL","longitude":104.432078,"latitude":2.88533,"baro_altitude":8085,"geo_altitude":8649,"on_ground":false,"velocity":223.9,"true_track":190.46,"vertical_rate":-7.8,"squawk":"5563","aircraft_type":"A21N","aircraft_desc":"AIRBUS A-321neo","registration":"9V-NCL"},{"icao24":"8a03e5","callsign":"PK-AZD","origin_country":"PK-AZD","longitude":104.575401,"latitude":0.395973,"baro_altitude":null,"geo_altitude":7742,"on_ground":false,"velocity":213.4,"true_track":156.71,"vertical_rate":null,"squawk":"2241","aircraft_type":"A320","aircraft_desc":"AIRBUS A-320","registration":"PK-AZD"},{"icao24":"06a122","callsign":"QTR963","origin_country":"A7-ANF","longitude":104.692178,"latitude":0.665511,"baro_altitude":11582,"geo_altitude":12375,"on_ground":false,"velocity":262.1,"true_track":303.88,"vertical_rate":0,"squawk":"4115","aircraft_type":"A35K","aircraft_desc":"AIRBUS A-350-1000","registration":"A7-ANF"},{"icao24":"76b44b","callsign":"SIA852","origin_country":"9V-MBK","longitude":104.72902,"latitude":3.092651,"baro_altitude":9190,"geo_altitude":9830,"on_ground":false,"velocity":234.1,"true_track":18.32,"vertical_rate":4.23,"squawk":"0172","aircraft_type":"B38M","aircraft_desc":"BOEING 737 MAX 8","registration":"9V-MBK"},{"icao24":"8a09c9","callsign":"AWQ252","origin_country":"PK-AZX","longitude":104.732574,"latitude":-2.001141,"baro_altitude":11590,"geo_altitude":null,"on_ground":false,"velocity":246.4,"true_track":341,"vertical_rate":-0.01,"squawk":"2330","aircraft_type":"A320","aircraft_desc":"AIRBUS A-320","registration":"PK-AZX"},{"icao24":"8a02ca","callsign":"AWQ241","origin_country":"PK-AXT","longitude":104.850677,"latitude":-0.248449,"baro_altitude":10668,"geo_altitude":null,"on_ground":false,"velocity":214.5,"true_track":155.3,"vertical_rate":0,"squawk":"0141","aircraft_type":"A320","aircraft_desc":"AIRBUS A-320","registration":"PK-AXT"},{"icao24":"758404","callsign":"PAL512","origin_country":"RP-C9929","longitude":104.924311,"latitude":1.342473,"baro_altitude":5624,"geo_altitude":6005,"on_ground":false,"velocity":201.2,"true_track":88.53,"vertical_rate":4.23,"squawk":"0142","aircraft_type":"A321","aircraft_desc":"AIRBUS A-321","registration":"RP-C9929"},{"icao24":"8a09c7","callsign":"SJV907","origin_country":"PK-STU","longitude":105.000298,"latitude":-2.720398,"baro_altitude":10660,"geo_altitude":null,"on_ground":false,"velocity":233.6,"true_track":143.1,"vertical_rate":-0.01,"squawk":"6241","aircraft_type":"A320","aircraft_desc":"AIRBUS A-320","registration":"PK-STU"},{"icao24":"8a0a3e","callsign":"TNU860","origin_country":"PK-TLG","longitude":105.42569,"latitude":-3.759293,"baro_altitude":8839,"geo_altitude":null,"on_ground":false,"velocity":243.8,"true_track":344.6,"vertical_rate":-0.02,"squawk":"7110","aircraft_type":"A321","aircraft_desc":"AIRBUS A-321","registration":"PK-TLG"},{"icao24":"8a0637","callsign":"BTK7055","origin_country":"PK-LUS","longitude":105.491104,"latitude":-4.417761,"baro_altitude":8534,"geo_altitude":null,"on_ground":false,"velocity":217.6,"true_track":333.3,"vertical_rate":-0.02,"squawk":"1762","aircraft_type":"A320","aircraft_desc":"AIRBUS A-320","registration":"PK-LUS"},{"icao24":"76cce4","callsign":"9V-SGD","origin_country":"9V-SGD","longitude":106.063176,"latitude":1.89505,"baro_altitude":8390,"geo_altitude":8969,"on_ground":false,"velocity":228.5,"true_track":27.49,"vertical_rate":3.9,"squawk":"2263","aircraft_type":"A359","aircraft_desc":"AIRBUS A-350-900","registration":"9V-SGD"},{"icao24":"76cd0d","callsign":"SIA214","origin_country":"9V-SHM","longitude":106.136596,"latitude":-7.984454,"baro_altitude":12192,"geo_altitude":12946,"on_ground":false,"velocity":250.8,"true_track":343.68,"vertical_rate":-0.33,"squawk":"1355","aircraft_type":"A359","aircraft_desc":"AIRBUS A-350-900","registration":"9V-SHM"},{"icao24":"76cef2","callsign":"SIA965","origin_country":"9V-SWR","longitude":106.291115,"latitude":-5.59921,"baro_altitude":6325,"geo_altitude":6728,"on_ground":false,"velocity":212.4,"true_track":340.03,"vertical_rate":13.33,"squawk":null,"aircraft_type":"B77W","aircraft_desc":"BOEING 777-300ER","registration":"9V-SWR"},{"icao24":"8a03f3","callsign":"AWQ324","origin_country":"PK-AZE","longitude":106.566719,"latitude":-0.76625,"baro_altitude":10973,"geo_altitude":null,"on_ground":false,"velocity":238.2,"true_track":311.6,"vertical_rate":0,"squawk":"7007","aircraft_type":"A320","aircraft_desc":"AIRBUS A-320","registration":"PK-AZE"},{"icao24":"8a0289","callsign":"GIA822","origin_country":"PK-GFP","longitude":106.610855,"latitude":-6.11985,"baro_altitude":541,"geo_altitude":572,"on_ground":false,"velocity":96.3,"true_track":291.63,"vertical_rate":null,"squawk":"2372","aircraft_type":"B738","aircraft_desc":"BOEING 737-800","registration":"PK-GFP"},{"icao24":"8a09f8","callsign":"TNU5110","origin_country":"PK-TLF","longitude":106.615685,"latitude":-6.026513,"baro_altitude":2896,"geo_altitude":3094,"on_ground":false,"velocity":153.2,"true_track":103.99,"vertical_rate":13.33,"squawk":"2346","aircraft_type":"A320","aircraft_desc":"AIRBUS A-320","registration":"PK-TLF"},{"icao24":"8a09d6","callsign":"GIA313","origin_country":"PK-GUC","longitude":106.706108,"latitude":-6.117691,"baro_altitude":221,"geo_altitude":244,"on_ground":false,"velocity":null,"true_track":null,"vertical_rate":null,"squawk":"6320","aircraft_type":"B738","aircraft_desc":"BOEING 737-800","registration":"PK-GUC"},{"icao24":"8a097e","callsign":"LNI033","origin_country":"PK-LRH","longitude":106.793644,"latitude":-6.082795,"baro_altitude":754,"geo_altitude":808,"on_ground":false,"velocity":71.6,"true_track":248.05,"vertical_rate":-2.93,"squawk":"4413","aircraft_type":"B39M","aircraft_desc":"BOEING 737 MAX 9","registration":"PK-LRH"},{"icao24":"7c492b","callsign":"QF2","origin_country":"VH-OQL","longitude":106.803246,"latitude":-2.683926,"baro_altitude":10668,"geo_altitude":null,"on_ground":false,"velocity":null,"true_track":128.03,"vertical_rate":null,"squawk":"0010","aircraft_type":"A388","aircraft_desc":"AIRBUS A-380-800","registration":"VH-OQL"},{"icao24":"7c6bbe","callsign":"JST17","origin_country":"VH-VKG","longitude":107.626961,"latitude":-1.589767,"baro_altitude":12192,"geo_altitude":null,"on_ground":false,"velocity":261.9,"true_track":310.2,"vertical_rate":-0.01,"squawk":"1447","aircraft_type":"B788","aircraft_desc":"BOEING 787-8 Dreamliner","registration":"VH-VKG"},{"icao24":"76cd19","callsign":"SIA215","origin_country":"9V-SHY","longitude":107.634686,"latitude":-7.602951,"baro_altitude":11887,"geo_altitude":12664,"on_ground":false,"velocity":256.4,"true_track":164.4,"vertical_rate":0,"squawk":"2233","aircraft_type":"A359","aircraft_desc":"AIRBUS A-350-900","registration":"9V-SHY"},{"icao24":"8016ba","callsign":"IGO1612","origin_country":"","longitude":108.037735,"latitude":-1.943665,"baro_altitude":11582,"geo_altitude":null,"on_ground":false,"velocity":242.8,"true_track":311,"vertical_rate":-0.01,"squawk":"4124","aircraft_type":null,"aircraft_desc":null,"registration":null},{"icao24":"71c209","callsign":"KAL437","origin_country":"HL8209","longitude":109.457214,"latitude":-2.496131,"baro_altitude":10973,"geo_altitude":null,"on_ground":false,"velocity":256.7,"true_track":218.9,"vertical_rate":-0.01,"squawk":"7112","aircraft_type":"B77W","aircraft_desc":"BOEING 777-300ER","registration":"HL8209"},{"icao24":"8a093a","callsign":"BTK6213","origin_country":"PK-BKL","longitude":109.771179,"latitude":-5.076196,"baro_altitude":10356,"geo_altitude":null,"on_ground":false,"velocity":236.6,"true_track":253,"vertical_rate":-0.03,"squawk":null,"aircraft_type":"A320","aircraft_desc":"AIRBUS A-320","registration":"PK-BKL"},{"icao24":"8a04d7","callsign":"GIA426","origin_country":"PK-GPW","longitude":111.023712,"latitude":-6.332222,"baro_altitude":11887,"geo_altitude":12703,"on_ground":false,"velocity":243.3,"true_track":53.25,"vertical_rate":0,"squawk":"2436","aircraft_type":"A333","aircraft_desc":"AIRBUS A-330-300","registration":"PK-GPW"},{"icao24":"8a040a","callsign":"GIA325","origin_country":"PK-GNA","longitude":111.132057,"latitude":-6.167427,"baro_altitude":10363,"geo_altitude":null,"on_ground":false,"velocity":238.7,"true_track":287.9,"vertical_rate":-0.03,"squawk":"6324","aircraft_type":"B738","aircraft_desc":"BOEING 737-800","registration":"PK-GNA"},{"icao24":"8a0515","callsign":"BTK7310","origin_country":"PK-LAL","longitude":111.53553,"latitude":-6.282028,"baro_altitude":10356,"geo_altitude":null,"on_ground":false,"velocity":236.6,"true_track":285.6,"vertical_rate":-0.03,"squawk":"4407","aircraft_type":"A320","aircraft_desc":"AIRBUS A-320","registration":"PK-LAL"},{"icao24":"76b447","callsign":"SIA929","origin_country":"9V-MBG","longitude":112.413956,"latitude":-6.820275,"baro_altitude":5563,"geo_altitude":null,"on_ground":false,"velocity":195.5,"true_track":324.5,"vertical_rate":-0.03,"squawk":"7011","aircraft_type":"B38M","aircraft_desc":"BOEING 737 MAX 8","registration":"9V-MBG"},{"icao24":"8a017c","callsign":"AWQ504","origin_country":"PK-AXD","longitude":112.414192,"latitude":-5.752786,"baro_altitude":10973,"geo_altitude":null,"on_ground":false,"velocity":236.6,"true_track":null,"vertical_rate":-0.03,"squawk":"4127","aircraft_type":"A320","aircraft_desc":"AIRBUS A-320","registration":"PK-AXD"},{"icao24":"75027c","callsign":"AXM5753","origin_country":"","longitude":112.93792,"latitude":4.760788,"baro_altitude":10371,"geo_altitude":11102,"on_ground":false,"velocity":244.9,"true_track":274.9,"vertical_rate":0.02,"squawk":"0427","aircraft_type":null,"aircraft_desc":null,"registration":null},{"icao24":"8a026a","callsign":"LNI923","origin_country":"PK-LHQ","longitude":113.534065,"latitude":-7.80542,"baro_altitude":6096,"geo_altitude":null,"on_ground":false,"velocity":174.9,"true_track":298.4,"vertical_rate":-0.04,"squawk":"4414","aircraft_type":"B739","aircraft_desc":"BOEING 737-900","registration":"PK-LHQ"},{"icao24":"8a09d9","callsign":"AWQ537","origin_country":"PK-AZW","longitude":115.710923,"latitude":-31.964256,"baro_altitude":2865,"geo_altitude":2979,"on_ground":false,"velocity":142.2,"true_track":357.1,"vertical_rate":13.98,"squawk":"1310","aircraft_type":"A320","aircraft_desc":"AIRBUS A-320","registration":"PK-AZW"},{"icao24":"7cf632","callsign":"","origin_country":"","longitude":115.958963,"latitude":-31.937302,"baro_altitude":0,"geo_altitude":null,"on_ground":true,"velocity":0,"true_track":null,"vertical_rate":null,"squawk":null,"aircraft_type":null,"aircraft_desc":null,"registration":null},{"icao24":"7cf64c","callsign":"TUG12","origin_country":"","longitude":115.959236,"latitude":-31.938152,"baro_altitude":0,"geo_altitude":null,"on_ground":true,"velocity":0.1,"true_track":null,"vertical_rate":null,"squawk":null,"aircraft_type":null,"aircraft_desc":null,"registration":null},{"icao24":"7cf67b","callsign":"","origin_country":"","longitude":115.960329,"latitude":-31.929226,"baro_altitude":0,"geo_altitude":null,"on_ground":true,"velocity":0,"true_track":106.88,"vertical_rate":null,"squawk":null,"aircraft_type":null,"aircraft_desc":null,"registration":null},{"icao24":"7cf5e7","callsign":"TUG82","origin_country":"","longitude":115.96159,"latitude":-31.933718,"baro_altitude":0,"geo_altitude":null,"on_ground":true,"velocity":1.1,"true_track":289.69,"vertical_rate":null,"squawk":null,"aircraft_type":null,"aircraft_desc":null,"registration":null},{"icao24":"7cf5d0","callsign":"TUG71","origin_country":"","longitude":115.961772,"latitude":-31.932915,"baro_altitude":0,"geo_altitude":null,"on_ground":true,"velocity":0,"true_track":null,"vertical_rate":null,"squawk":null,"aircraft_type":null,"aircraft_desc":null,"registration":null},{"icao24":"7cf631","callsign":"1DZD775","origin_country":"","longitude":115.962314,"latitude":-31.936775,"baro_altitude":0,"geo_altitude":null,"on_ground":true,"velocity":0,"true_track":null,"vertical_rate":null,"squawk":null,"aircraft_type":null,"aircraft_desc":null,"registration":null},{"icao24":"~7cf66d","callsign":"TM28","origin_country":"","longitude":115.964648,"latitude":-31.922779,"baro_altitude":0,"geo_altitude":null,"on_ground":true,"velocity":0.6,"true_track":284.06,"vertical_rate":null,"squawk":null,"aircraft_type":null,"aircraft_desc":null,"registration":null},{"icao24":"7cf5f4","callsign":"","origin_country":"","longitude":115.96815,"latitude":-31.948128,"baro_altitude":0,"geo_altitude":null,"on_ground":true,"velocity":6.6,"true_track":236.25,"vertical_rate":null,"squawk":null,"aircraft_type":null,"aircraft_desc":null,"registration":null},{"icao24":"750585","callsign":"AXM606","origin_country":"9M-VAG","longitude":115.969648,"latitude":-31.939176,"baro_altitude":0,"geo_altitude":null,"on_ground":true,"velocity":5.8,"true_track":0,"vertical_rate":-0.16,"squawk":"2174","aircraft_type":"A21N","aircraft_desc":"AIRBUS A-321neo","registration":"9M-VAG"},{"icao24":"7cf5eb","callsign":"TUG86","origin_country":"","longitude":115.970389,"latitude":-31.940735,"baro_altitude":0,"geo_altitude":null,"on_ground":true,"velocity":0,"true_track":null,"vertical_rate":null,"squawk":null,"aircraft_type":null,"aircraft_desc":null,"registration":null},{"icao24":"7cf64e","callsign":"TUG14","origin_country":"","longitude":115.973204,"latitude":-31.940506,"baro_altitude":0,"geo_altitude":null,"on_ground":true,"velocity":0,"true_track":null,"vertical_rate":null,"squawk":null,"aircraft_type":null,"aircraft_desc":null,"registration":null},{"icao24":"7cf64f","callsign":"TUG15","origin_country":"","longitude":115.974006,"latitude":-31.940386,"baro_altitude":0,"geo_altitude":null,"on_ground":true,"velocity":null,"true_track":null,"vertical_rate":null,"squawk":null,"aircraft_type":null,"aircraft_desc":null,"registration":null},{"icao24":"7cf84a","callsign":"PHNX07","origin_country":"A27-016","longitude":115.996231,"latitude":-31.736772,"baro_altitude":975,"geo_altitude":null,"on_ground":false,"velocity":null,"true_track":null,"vertical_rate":0.29,"squawk":"2052","aircraft_type":"HAWK","aircraft_desc":"BRITISH AEROSPACE T-45 Goshawk","registration":"A27-016"},{"icao24":"7c77f6","callsign":"QFA891","origin_country":"VH-XZC","longitude":116.018708,"latitude":-31.910442,"baro_altitude":198,"geo_altitude":236,"on_ground":false,"velocity":71.2,"true_track":237.69,"vertical_rate":-2.93,"squawk":"4004","aircraft_type":"B738","aircraft_desc":"BOEING 737-800","registration":"VH-XZC"},{"icao24":"7caf16","callsign":"VOZ1866","origin_country":"VH-8VC","longitude":116.169265,"latitude":-31.833258,"baro_altitude":1082,"geo_altitude":1143,"on_ground":false,"velocity":103.4,"true_track":238.84,"vertical_rate":-5.2,"squawk":"3664","aircraft_type":"B38M","aircraft_desc":"BOEING 737 MAX 8","registration":"VH-8VC"},{"icao24":"782205","callsign":"CSN8137","origin_country":"B-32L0","longitude":116.279111,"latitude":5.205734,"baro_altitude":9754,"geo_altitude":10470,"on_ground":false,"velocity":232.3,"true_track":157.47,"vertical_rate":0,"squawk":"3130","aircraft_type":"A21N","aircraft_desc":"AIRBUS A-321neo","registration":"B-32L0"},{"icao24":"7c6842","callsign":"NWK1737","origin_country":"VH-UVO","longitude":116.317749,"latitude":-31.359217,"baro_altitude":3452,"geo_altitude":3658,"on_ground":false,"velocity":201.6,"true_track":198.76,"vertical_rate":-16.42,"squawk":"7212","aircraft_type":"A320","aircraft_desc":"AIRBUS A-320","registration":"VH-UVO"},{"icao24":"7c2539","callsign":"HMZ","origin_country":"VH-HMZ","longitude":116.5901,"latitude":-31.959686,"baro_altitude":4267,"geo_altitude":4427,"on_ground":false,"velocity":129.4,"true_track":256.9,"vertical_rate":0,"squawk":"4267","aircraft_type":"C441","aircraft_desc":"CESSNA 441 Conquest","registration":"VH-HMZ"},{"icao24":"7c42e4","callsign":"NWK1651","origin_country":"VH-NHY","longitude":116.697208,"latitude":-30.248611,"baro_altitude":9754,"geo_altitude":10157,"on_ground":false,"velocity":210.9,"true_track":190.54,"vertical_rate":null,"squawk":"4375","aircraft_type":"F100","aircraft_desc":"FOKKER 100","registration":"VH-NHY"},{"icao24":"7cae05","callsign":"NWK1657","origin_country":"VH-8NR","longitude":117.25782,"latitude":-29.224915,"baro_altitude":11575,"geo_altitude":12032,"on_ground":false,"velocity":226.4,"true_track":202.02,"vertical_rate":0.33,"squawk":"1104","aircraft_type":"A319","aircraft_desc":"AIRBUS A-319","registration":"VH-8NR"},{"icao24":"7c1b06","callsign":"VHFMG","origin_country":"VH-FMG","longitude":119.110693,"latitude":-31.708964,"baro_altitude":10950,"geo_altitude":11346,"on_ground":false,"velocity":271.3,"true_track":85.98,"vertical_rate":4.55,"squawk":"1526","aircraft_type":"GL7T","aircraft_desc":"BOMBARDIER BD-700 Global 7000/7500","registration":"VH-FMG"},{"icao24":"7c7a49","callsign":"VOZ691","origin_country":"VH-YFV","longitude":119.176941,"latitude":-33.624252,"baro_altitude":9136,"geo_altitude":null,"on_ground":false,"velocity":158.4,"true_track":301,"vertical_rate":-0.17,"squawk":"3676","aircraft_type":"B738","aircraft_desc":"BOEING 737-800","registration":"VH-YFV"},{"icao24":"7c7ab8","callsign":"VOZ699","origin_country":"VH-YIY","longitude":119.353271,"latitude":-32.921219,"baro_altitude":9144,"geo_altitude":9479,"on_ground":false,"velocity":227.3,"true_track":290.81,"vertical_rate":null,"squawk":null,"aircraft_type":"B738","aircraft_desc":"BOEING 737-800","registration":"VH-YIY"},{"icao24":"76cc82","callsign":"SQ276","origin_country":"","longitude":119.550133,"latitude":-13.330193,"baro_altitude":11580,"geo_altitude":null,"on_ground":false,"velocity":244.9,"true_track":316.31,"vertical_rate":0,"squawk":"0010","aircraft_type":null,"aircraft_desc":null,"registration":null},{"icao24":"c8215f","callsign":"ZK-OKS","origin_country":"ZK-OKS","longitude":120.090509,"latitude":-33.118469,"baro_altitude":10668,"geo_altitude":11011,"on_ground":false,"velocity":null,"true_track":null,"vertical_rate":null,"squawk":null,"aircraft_type":"B77W","aircraft_desc":"BOEING 777-300ER","registration":"ZK-OKS"},{"icao24":"7c4a11","callsign":"FD623","origin_country":"VH-OWZ","longitude":121.335808,"latitude":-30.706833,"baro_altitude":2827,"geo_altitude":2957,"on_ground":false,"velocity":84.5,"true_track":309.31,"vertical_rate":6.5,"squawk":"3000","aircraft_type":"PC12","aircraft_desc":"PILATUS PC-12","registration":"VH-OWZ"},{"icao24":"758532","callsign":"CEB956","origin_country":"RP-C4113","longitude":123.036274,"latitude":11.119654,"baro_altitude":10363,"geo_altitude":11148,"on_ground":false,"velocity":247.6,"true_track":329.81,"vertical_rate":0,"squawk":"4007","aircraft_type":"A321","aircraft_desc":"AIRBUS A-321","registration":"RP-C4113"},{"icao24":"75833a","callsign":"PAL1863","origin_country":"RP-C8766","longitude":123.285249,"latitude":11.897169,"baro_altitude":9647,"geo_altitude":10409,"on_ground":false,"velocity":247.8,"true_track":143.87,"vertical_rate":-11.38,"squawk":"4057","aircraft_type":"A333","aircraft_desc":"AIRBUS A-330-300","registration":"RP-C8766"},{"icao24":"75853a","callsign":"APG330","origin_country":"RP-C8965","longitude":123.439492,"latitude":12.803774,"baro_altitude":9754,"geo_altitude":10455,"on_ground":false,"velocity":220.5,"true_track":311.5,"vertical_rate":null,"squawk":"4046","aircraft_type":"A320","aircraft_desc":"AIRBUS A-320","registration":"RP-C8965"},{"icao24":"758475","callsign":"GAP2288","origin_country":"RP-C5902","longitude":123.490637,"latitude":10.488876,"baro_altitude":3810,"geo_altitude":4100,"on_ground":false,"velocity":139.8,"true_track":137.39,"vertical_rate":-6.18,"squawk":"4270","aircraft_type":"DH8D","aircraft_desc":"DE HAVILLAND DHC-8-400 Dash 8","registration":"RP-C5902"},{"icao24":"758707","callsign":"CEB573","origin_country":"RP-C3905","longitude":123.769598,"latitude":10.459946,"baro_altitude":2301,"geo_altitude":2507,"on_ground":false,"velocity":143.3,"true_track":185.98,"vertical_rate":-6.5,"squawk":"4245","aircraft_type":"A339","aircraft_desc":"AIRBUS A-330-900","registration":"RP-C3905"},{"icao24":"7c1469","callsign":"QFA7535","origin_country":"VH-EBF","longitude":123.864585,"latitude":11.029529,"baro_altitude":11582,"geo_altitude":12428,"on_ground":false,"velocity":242.1,"true_track":350.34,"vertical_rate":-0.33,"squawk":"1555","aircraft_type":"A332","aircraft_desc":"AIRBUS A-330-200","registration":"VH-EBF"},{"icao24":"75824e","callsign":"GAP2527","origin_country":"RP-C8397","longitude":123.86493,"latitude":11.025238,"baro_altitude":10668,"geo_altitude":11468,"on_ground":false,"velocity":236.2,"true_track":169.84,"vertical_rate":0,"squawk":"4264","aircraft_type":"A320","aircraft_desc":"AIRBUS A-320","registration":"RP-C8397"},{"icao24":"758502","callsign":"APG778","origin_country":"RP-C8963","longitude":123.974865,"latitude":10.302999,"baro_altitude":0,"geo_altitude":null,"on_ground":true,"velocity":27.5,"true_track":45,"vertical_rate":null,"squawk":"4026","aircraft_type":"A320","aircraft_desc":"AIRBUS A-320","registration":"RP-C8963"},{"icao24":"7583f8","callsign":"CEB4084","origin_country":"RP-C4108","longitude":123.979142,"latitude":10.313702,"baro_altitude":0,"geo_altitude":null,"on_ground":true,"velocity":0,"true_track":null,"vertical_rate":null,"squawk":"4051","aircraft_type":"A320","aircraft_desc":"AIRBUS A-320","registration":"RP-C4108"},{"icao24":"7c4a57","callsign":"JST100","origin_country":"","longitude":124.075233,"latitude":10.373933,"baro_altitude":983,"geo_altitude":1097,"on_ground":false,"velocity":136.7,"true_track":105.5,"vertical_rate":13.33,"squawk":"6572","aircraft_type":null,"aircraft_desc":null,"registration":null},{"icao24":"758768","callsign":"RP-C4264","origin_country":"RP-C4264","longitude":124.595016,"latitude":8.779816,"baro_altitude":3338,"geo_altitude":3604,"on_ground":false,"velocity":126.5,"true_track":143.27,"vertical_rate":-4.55,"squawk":null,"aircraft_type":"A20N","aircraft_desc":"AIRBUS A-320neo","registration":"RP-C4264"},{"icao24":"7585a0","callsign":"SRQ6924","origin_country":"RP-C7291","longitude":124.61266,"latitude":9.74707,"baro_altitude":4267,"geo_altitude":4496,"on_ground":false,"velocity":125.2,"true_track":296.35,"vertical_rate":0,"squawk":"4037","aircraft_type":"AT76","aircraft_desc":"ATR-72-600","registration":"RP-C7291"},{"icao24":"758538","callsign":"APG523","origin_country":"RP-C8967","longitude":124.776477,"latitude":9.628281,"baro_altitude":7841,"geo_altitude":8382,"on_ground":false,"velocity":217,"true_track":145.82,"vertical_rate":5.2,"squawk":"4276","aircraft_type":"A320","aircraft_desc":"AIRBUS A-320","registration":"RP-C8967"},{"icao24":"75876f","callsign":"CEB591","origin_country":"RP-C4135","longitude":125.584054,"latitude":7.937203,"baro_altitude":4488,"geo_altitude":4846,"on_ground":false,"velocity":184.6,"true_track":167.28,"vertical_rate":-10.4,"squawk":"4244","aircraft_type":"A20N","aircraft_desc":"AIRBUS A-320neo","registration":"RP-C4135"},{"icao24":"758534","callsign":"CEB959","origin_country":"RP-C4115","longitude":125.642146,"latitude":7.122341,"baro_altitude":0,"geo_altitude":null,"on_ground":true,"velocity":2.7,"true_track":227.81,"vertical_rate":null,"squawk":"4047","aircraft_type":"A321","aircraft_desc":"AIRBUS A-321","registration":"RP-C4115"},{"icao24":"7c1467","callsign":"QF775","origin_country":"VH-EBD","longitude":127.498569,"latitude":-38.005829,"baro_altitude":12191,"geo_altitude":null,"on_ground":false,"velocity":205.8,"true_track":287.76,"vertical_rate":0.08,"squawk":"0010","aircraft_type":"A332","aircraft_desc":"AIRBUS A-330-200","registration":"VH-EBD"},{"icao24":"7c29d5","callsign":"VOZ702","origin_country":"VH-IJR","longitude":135.006485,"latitude":-37.032898,"baro_altitude":11278,"geo_altitude":11339,"on_ground":false,"velocity":305.1,"true_track":101.1,"vertical_rate":-0.19,"squawk":"4060","aircraft_type":"P28A","aircraft_desc":"PIPER PA-28-140/150/160/180","registration":"VH-IJR"},{"icao24":"7c6b0c","callsign":"JST988","origin_country":"VH-VFI","longitude":135.109463,"latitude":-35.180736,"baro_altitude":8534,"geo_altitude":8733,"on_ground":false,"velocity":193.3,"true_track":266.19,"vertical_rate":0.65,"squawk":"4063","aircraft_type":"A320","aircraft_desc":"AIRBUS A-320","registration":"VH-VFI"},{"icao24":"8a018c","callsign":"AWQ423","origin_country":"PK-AXE","longitude":136.595654,"latitude":-33.403564,"baro_altitude":10363,"geo_altitude":10698,"on_ground":false,"velocity":179.7,"true_track":318.6,"vertical_rate":0.33,"squawk":"1505","aircraft_type":"A320","aircraft_desc":"AIRBUS A-320","registration":"PK-AXE"},{"icao24":"7c2bb0","callsign":"VOZ703","origin_country":"VH-IWY","longitude":136.678619,"latitude":-35.896774,"baro_altitude":10973,"geo_altitude":11133,"on_ground":false,"velocity":157.2,"true_track":279.8,"vertical_rate":0.81,"squawk":"6767","aircraft_type":"B738","aircraft_desc":"BOEING 737-800","registration":"VH-IWY"},{"icao24":"7c6d2f","callsign":"VOZ569","origin_country":"VH-VUP","longitude":136.748227,"latitude":-35.080856,"baro_altitude":7315,"geo_altitude":7483,"on_ground":false,"velocity":193.1,"true_track":265.26,"vertical_rate":0,"squawk":"4031","aircraft_type":"B738","aircraft_desc":"BOEING 737-800","registration":"VH-VUP"},{"icao24":"896480","callsign":"UAE43P","origin_country":"A6-EUV","longitude":137.064787,"latitude":-36.686189,"baro_altitude":9754,"geo_altitude":9815,"on_ground":false,"velocity":197.1,"true_track":284.51,"vertical_rate":0,"squawk":"1541","aircraft_type":"A388","aircraft_desc":"AIRBUS A-380-800","registration":"A6-EUV"},{"icao24":"7c6dc9","callsign":"QFA857","origin_country":"VH-VYZ","longitude":137.773476,"latitude":-36.298096,"baro_altitude":8527,"geo_altitude":8633,"on_ground":false,"velocity":178.3,"true_track":273.14,"vertical_rate":0,"squawk":"7240","aircraft_type":"B738","aircraft_desc":"BOEING 737-800","registration":"VH-VYZ"},{"icao24":"7c6d31","callsign":"VH-VUR","origin_country":"VH-VUR","longitude":138.540596,"latitude":-34.938332,"baro_altitude":0,"geo_altitude":null,"on_ground":true,"velocity":3.7,"true_track":320.62,"vertical_rate":null,"squawk":"1017","aircraft_type":"B738","aircraft_desc":"BOEING 737-800","registration":"VH-VUR"},{"icao24":"7c68cc","callsign":"QLK1905","origin_country":"VH-UZI","longitude":138.573023,"latitude":-34.920135,"baro_altitude":213,"geo_altitude":213,"on_ground":false,"velocity":58.4,"true_track":230,"vertical_rate":-3.9,"squawk":"1136","aircraft_type":"E190","aircraft_desc":"EMBRAER ERJ-190-100","registration":"VH-UZI"},{"icao24":"7cad47","callsign":"VOZ092","origin_country":"VH-8IH","longitude":138.617249,"latitude":-34.97493,"baro_altitude":11278,"geo_altitude":11537,"on_ground":false,"velocity":317.1,"true_track":111.61,"vertical_rate":0,"squawk":"4101","aircraft_type":"B38M","aircraft_desc":"BOEING 737 MAX 8","registration":"VH-8IH"},{"icao24":"7c6d32","callsign":"VOZ722","origin_country":"VH-VUS","longitude":138.736382,"latitude":-34.8052,"baro_altitude":1265,"geo_altitude":1288,"on_ground":false,"velocity":110.9,"true_track":210.37,"vertical_rate":-6.99,"squawk":"4317","aircraft_type":"B738","aircraft_desc":"BOEING 737-800","registration":"VH-VUS"},{"icao24":"7c6b39","callsign":"JST780","origin_country":"VH-VGR","longitude":138.907658,"latitude":-34.854858,"baro_altitude":1844,"geo_altitude":1875,"on_ground":false,"velocity":122.6,"true_track":324.04,"vertical_rate":-6.01,"squawk":"4213","aircraft_type":"A320","aircraft_desc":"AIRBUS A-320","registration":"VH-VGR"},{"icao24":"7c6db3","callsign":"QFA749","origin_country":"VH-VYD","longitude":139.272953,"latitude":-34.779831,"baro_altitude":4039,"geo_altitude":4130,"on_ground":false,"velocity":122.5,"true_track":268.56,"vertical_rate":-7.8,"squawk":"4327","aircraft_type":"B738","aircraft_desc":"BOEING 737-800","registration":"VH-VYD"},{"icao24":"780daf","callsign":"CSN344","origin_country":"B-5966","longitude":140.037824,"latitude":-30.456116,"baro_altitude":10363,"geo_altitude":10889,"on_ground":false,"velocity":null,"true_track":null,"vertical_rate":null,"squawk":null,"aircraft_type":"A333","aircraft_desc":"AIRBUS A-330-300","registration":"B-5966"},{"icao24":"7c56b7","callsign":"VOZ579","origin_country":"VH-REX","longitude":140.247597,"latitude":-34.746826,"baro_altitude":10912,"geo_altitude":11224,"on_ground":false,"velocity":149.3,"true_track":267.43,"vertical_rate":-17.23,"squawk":"3745","aircraft_type":"B738","aircraft_desc":"BOEING 737-800","registration":"VH-REX"},{"icao24":"7c6d2b","callsign":"VOZ1465","origin_country":"VH-VUL","longitude":140.557819,"latitude":-31.546403,"baro_altitude":10973,"geo_altitude":11476,"on_ground":false,"velocity":200.4,"true_track":341.29,"vertical_rate":0.49,"squawk":"1256","aircraft_type":"B738","aircraft_desc":"BOEING 737-800","registration":"VH-VUL"},{"icao24":"7c6b38","callsign":"JST621","origin_country":"VH-VGQ","longitude":141.195938,"latitude":-36.561616,"baro_altitude":11582,"geo_altitude":11788,"on_ground":false,"velocity":160.5,"true_track":294.84,"vertical_rate":-0.49,"squawk":"7176","aircraft_type":"A320","aircraft_desc":"AIRBUS A-320","registration":"VH-VGQ"},{"icao24":"78160e","callsign":"CES740","origin_country":"B-208X","longitude":141.481491,"latitude":-32.853928,"baro_altitude":10363,"geo_altitude":10790,"on_ground":false,"velocity":223.2,"true_track":343.53,"vertical_rate":-0.16,"squawk":"1350","aircraft_type":"B789","aircraft_desc":"BOEING 787-9 Dreamliner","registration":"B-208X"},{"icao24":"7c4811","callsign":"JST044","origin_country":"VH-OIR","longitude":141.614938,"latitude":-36.233376,"baro_altitude":10668,"geo_altitude":10889,"on_ground":false,"velocity":270.9,"true_track":160.36,"vertical_rate":0,"squawk":"4105","aircraft_type":"A21N","aircraft_desc":"AIRBUS A-321neo","registration":"VH-OIR"},{"icao24":"7c6b28","callsign":"JST782","origin_country":"VH-VGA","longitude":142.251036,"latitude":-36.880871,"baro_altitude":9136,"geo_altitude":9304,"on_ground":false,"velocity":182.5,"true_track":291.5,"vertical_rate":-0.49,"squawk":"6775","aircraft_type":"A320","aircraft_desc":"AIRBUS A-320","registration":"VH-VGA"},{"icao24":"7c7aa5","callsign":"VOZ1407","origin_country":"VH-YIF","longitude":142.807632,"latitude":-33.41259,"baro_altitude":12344,"geo_altitude":null,"on_ground":false,"velocity":287.6,"true_track":67.8,"vertical_rate":-0.17,"squawk":"1276","aircraft_type":"B738","aircraft_desc":"BOEING 737-800","registration":"VH-YIF"},{"icao24":"750523","callsign":"XAX213","origin_country":"9M-XBG","longitude":142.99942,"latitude":-35.847565,"baro_altitude":10973,"geo_altitude":11247,"on_ground":false,"velocity":177.8,"true_track":323,"vertical_rate":0,"squawk":"1401","aircraft_type":"A333","aircraft_desc":"AIRBUS A-330-300","registration":"9M-XBG"},{"icao24":"c829c8","callsign":"QFA7281","origin_country":"","longitude":144.238567,"latitude":-37.809769,"baro_altitude":3818,"geo_altitude":3871,"on_ground":false,"velocity":184.1,"true_track":81.64,"vertical_rate":-12.03,"squawk":"4360","aircraft_type":null,"aircraft_desc":null,"registration":null},{"icao24":"7586ce","callsign":"CEB049","origin_country":"RP-C3901","longitude":144.41906,"latitude":-36.60878,"baro_altitude":5837,"geo_altitude":5982,"on_ground":false,"velocity":198.7,"true_track":156.02,"vertical_rate":-6.18,"squawk":"1102","aircraft_type":"A339","aircraft_desc":"AIRBUS A-330-900","registration":"RP-C3901"},{"icao24":"7c4ef2","callsign":"POL30","origin_country":"VH-PVO","longitude":144.586448,"latitude":-37.821762,"baro_altitude":152,"geo_altitude":91,"on_ground":false,"velocity":6,"true_track":289.98,"vertical_rate":-0.98,"squawk":"0030","aircraft_type":"A139","aircraft_desc":"AGUSTA AW-139","registration":"VH-PVO"},{"icao24":"7c045c","callsign":"JST799","origin_country":"VH-A5A","longitude":144.725238,"latitude":-37.135712,"baro_altitude":3498,"geo_altitude":3551,"on_ground":false,"velocity":184.9,"true_track":170.07,"vertical_rate":-6.83,"squawk":"1043","aircraft_type":"A20N","aircraft_desc":"AIRBUS A-320neo","registration":"VH-A5A"},{"icao24":"7c6c90","callsign":"JST712","origin_country":"VH-VQA","longitude":144.841778,"latitude":-37.667679,"baro_altitude":0,"geo_altitude":137,"on_ground":true,"velocity":9,"true_track":140.62,"vertical_rate":null,"squawk":"3606","aircraft_type":"A320","aircraft_desc":"AIRBUS A-320","registration":"VH-VQA"},{"icao24":"7cf6f9","callsign":"","origin_country":"","longitude":144.844028,"latitude":-37.669247,"baro_altitude":0,"geo_altitude":null,"on_ground":true,"velocity":null,"true_track":null,"vertical_rate":null,"squawk":null,"aircraft_type":null,"aircraft_desc":null,"registration":null},{"icao24":"7c7ab0","callsign":"VOZ1380","origin_country":"VH-YIQ","longitude":144.846198,"latitude":-37.672003,"baro_altitude":0,"geo_altitude":null,"on_ground":true,"velocity":2.5,"true_track":264.38,"vertical_rate":null,"squawk":"3615","aircraft_type":"B738","aircraft_desc":"BOEING 737-800","registration":"VH-YIQ"},{"icao24":"7cf09f","callsign":"","origin_country":"","longitude":144.846258,"latitude":-37.676064,"baro_altitude":0,"geo_altitude":null,"on_ground":true,"velocity":5,"true_track":174.38,"vertical_rate":null,"squawk":null,"aircraft_type":null,"aircraft_desc":null,"registration":null},{"icao24":"~7cf09c","callsign":"TM23","origin_country":"","longitude":144.846541,"latitude":-37.681011,"baro_altitude":0,"geo_altitude":null,"on_ground":true,"velocity":5.6,"true_track":171.56,"vertical_rate":null,"squawk":null,"aircraft_type":null,"aircraft_desc":null,"registration":null},{"icao24":"8881de","callsign":"VJC81","origin_country":"VN-A817","longitude":144.846906,"latitude":-37.717072,"baro_altitude":358,"geo_altitude":312,"on_ground":false,"velocity":63.1,"true_track":350.61,"vertical_rate":-3.58,"squawk":"5027","aircraft_type":"A333","aircraft_desc":"AIRBUS A-330-300","registration":"VN-A817"},{"icao24":"7c431c","callsign":"JTE7487","origin_country":"VH-NJI","longitude":144.848213,"latitude":-37.677589,"baro_altitude":0,"geo_altitude":null,"on_ground":true,"velocity":2,"true_track":null,"vertical_rate":null,"squawk":null,"aircraft_type":"B463","aircraft_desc":"BRITISH AEROSPACE 146-300","registration":"VH-NJI"},{"icao24":"7c6d94","callsign":"VH-VXI","origin_country":"VH-VXI","longitude":144.849139,"latitude":-37.667173,"baro_altitude":0,"geo_altitude":null,"on_ground":true,"velocity":0,"true_track":null,"vertical_rate":null,"squawk":"3000","aircraft_type":"B738","aircraft_desc":"BOEING 737-800","registration":"VH-VXI"},{"icao24":"7c7a3e","callsign":"VOZ892","origin_country":"VH-YFK","longitude":144.889546,"latitude":-37.831467,"baro_altitude":1097,"geo_altitude":1074,"on_ground":false,"velocity":87.8,"true_track":264.96,"vertical_rate":-4.06,"squawk":"4010","aircraft_type":"B738","aircraft_desc":"BOEING 737-800","registration":"VH-YFK"},{"icao24":"7c585f","callsign":"VOZ1334","origin_country":"VH-RQP","longitude":144.957412,"latitude":-37.584549,"baro_altitude":2553,"geo_altitude":2553,"on_ground":false,"velocity":172.1,"true_track":151.83,"vertical_rate":9.27,"squawk":"3723","aircraft_type":"B738","aircraft_desc":"BOEING 737-800","registration":"VH-RQP"},{"icao24":"7c6b13","callsign":"JST738","origin_country":"VH-VFP","longitude":145.054769,"latitude":-37.885162,"baro_altitude":1669,"geo_altitude":1676,"on_ground":false,"velocity":120.9,"true_track":289.13,"vertical_rate":-8.13,"squawk":"4222","aircraft_type":"A320","aircraft_desc":"AIRBUS A-320","registration":"VH-VFP"},{"icao24":"7c6c52","callsign":"VOZ359","origin_country":"VH-VOK","longitude":145.150958,"latitude":-36.693638,"baro_altitude":9091,"geo_altitude":9335,"on_ground":false,"velocity":229.8,"true_track":49,"vertical_rate":7.32,"squawk":"1523","aircraft_type":"B738","aircraft_desc":"BOEING 737-800","registration":"VH-VOK"},{"icao24":"7c4ef4","callsign":"POL31","origin_country":"VH-PVQ","longitude":145.280054,"latitude":-37.8581,"baro_altitude":792,"geo_altitude":null,"on_ground":false,"velocity":30.9,"true_track":288.28,"vertical_rate":-3.41,"squawk":"0031","aircraft_type":"A139","aircraft_desc":"AGUSTA AW-139","registration":"VH-PVQ"},{"icao24":"7c7800","callsign":"QFA158","origin_country":"VH-XZM","longitude":145.68923,"latitude":-37.6772,"baro_altitude":5166,"geo_altitude":5250,"on_ground":false,"velocity":133.4,"true_track":267.35,"vertical_rate":-9.59,"squawk":"0273","aircraft_type":"B738","aircraft_desc":"BOEING 737-800","registration":"VH-XZM"},{"icao24":"7c788b","callsign":"JST216","origin_country":"VH-X3H","longitude":145.957109,"latitude":-37.68988,"baro_altitude":6027,"geo_altitude":6180,"on_ground":false,"velocity":139.9,"true_track":268.95,"vertical_rate":-9.27,"squawk":"0274","aircraft_type":"A20N","aircraft_desc":"AIRBUS A-320neo","registration":"VH-X3H"},{"icao24":"7c78ac","callsign":"QLK1259","origin_country":"VH-X4E","longitude":146.03752,"latitude":-35.765898,"baro_altitude":8534,"geo_altitude":8824,"on_ground":false,"velocity":222.4,"true_track":226.97,"vertical_rate":0,"squawk":"1167","aircraft_type":"BCS1","aircraft_desc":"AIRBUS A220-100","registration":"VH-X4E"},{"icao24":"7c7a3b","callsign":"VOZ291","origin_country":"VH-YFH","longitude":146.154688,"latitude":-36.581307,"baro_altitude":9441,"geo_altitude":9716,"on_ground":false,"velocity":234.8,"true_track":103.94,"vertical_rate":-1.14,"squawk":"4020","aircraft_type":"B738","aircraft_desc":"BOEING 737-800","registration":"VH-YFH"},{"icao24":"7c68c9","callsign":"QLK1870","origin_country":"VH-UZF","longitude":146.769803,"latitude":-19.256065,"baro_altitude":0,"geo_altitude":null,"on_ground":true,"velocity":0,"true_track":null,"vertical_rate":null,"squawk":"6056","aircraft_type":"E190","aircraft_desc":"EMBRAER ERJ-190-100","registration":"VH-UZF"},{"icao24":"7c6b0d","callsign":"JST613","origin_country":"VH-VFJ","longitude":146.873123,"latitude":-36.78353,"baro_altitude":10973,"geo_altitude":11270,"on_ground":false,"velocity":182.3,"true_track":241.7,"vertical_rate":5.04,"squawk":"4303","aircraft_type":"A320","aircraft_desc":"AIRBUS A-320","registration":"VH-VFJ"},{"icao24":"7c29d4","callsign":"VOZ353","origin_country":"VH-IJQ","longitude":147.212257,"latitude":-34.865616,"baro_altitude":11887,"geo_altitude":12261,"on_ground":false,"velocity":269.3,"true_track":41.52,"vertical_rate":0.16,"squawk":"1522","aircraft_type":"B738","aircraft_desc":"BOEING 737-800","registration":"VH-IJQ"},{"icao24":"89647f","callsign":"UAE5AM","origin_country":"A6-EUU","longitude":147.678324,"latitude":-21.470916,"baro_altitude":10058,"geo_altitude":10790,"on_ground":false,"velocity":249.4,"true_track":299.95,"vertical_rate":0,"squawk":"0272","aircraft_type":"A388","aircraft_desc":"AIRBUS A-380-800","registration":"A6-EUU"},{"icao24":"7c6c55","callsign":"VOZ799","origin_country":"VH-VON","longitude":147.74213,"latitude":-19.021545,"baro_altitude":12192,"geo_altitude":13000,"on_ground":false,"velocity":232.5,"true_track":323.64,"vertical_rate":-0.49,"squawk":"6024","aircraft_type":"B738","aircraft_desc":"BOEING 737-800","registration":"VH-VON"},{"icao24":"781dac","callsign":"CSN302","origin_country":"B-329S","longitude":147.944092,"latitude":-30.331995,"baro_altitude":10973,"geo_altitude":11552,"on_ground":false,"velocity":226.4,"true_track":325,"vertical_rate":-0.15,"squawk":"1512","aircraft_type":"A359","aircraft_desc":"AIRBUS A-350-900","registration":"B-329S"},{"icao24":"7c6b36","callsign":"JST934","origin_country":"VH-VGO","longitude":148.129161,"latitude":-19.569583,"baro_altitude":10965,"geo_altitude":11735,"on_ground":false,"velocity":237,"true_track":324.27,"vertical_rate":1.46,"squawk":"4401","aircraft_type":"A320","aircraft_desc":"AIRBUS A-320","registration":"VH-VGO"},{"icao24":"7c6d7f","callsign":"JST449","origin_country":"VH-VWX","longitude":148.170029,"latitude":-33.205897,"baro_altitude":8542,"geo_altitude":8938,"on_ground":false,"velocity":225.2,"true_track":217.58,"vertical_rate":1.63,"squawk":"1210","aircraft_type":"A321","aircraft_desc":"AIRBUS A-321","registration":"VH-VWX"},{"icao24":"7c7bd1","callsign":"VOZ471","origin_country":"VH-YQR","longitude":148.545012,"latitude":-29.704238,"baro_altitude":11582,"geo_altitude":12230,"on_ground":false,"velocity":277.4,"true_track":75.06,"vertical_rate":0,"squawk":"1346","aircraft_type":"B738","aircraft_desc":"BOEING 737-800","registration":"VH-YQR"},{"icao24":"86ebfa","callsign":"ANA880","origin_country":"JA888A","longitude":148.635661,"latitude":-25.205521,"baro_altitude":10965,"geo_altitude":11720,"on_ground":false,"velocity":260.6,"true_track":10.58,"vertical_rate":-0.13,"squawk":"1420","aircraft_type":"B789","aircraft_desc":"BOEING 787-9 Dreamliner","registration":"JA888A"},{"icao24":"7c4319","callsign":"JTE7484","origin_country":"VH-NJF","longitude":148.806283,"latitude":-34.418976,"baro_altitude":8260,"geo_altitude":8557,"on_ground":false,"velocity":231.9,"true_track":77.44,"vertical_rate":null,"squawk":"4216","aircraft_type":"B463","aircraft_desc":"BRITISH AEROSPACE 146-300","registration":"VH-NJF"},{"icao24":"7c531d","callsign":"QFA25","origin_country":"VH-QPB","longitude":148.835732,"latitude":-19.521262,"baro_altitude":10363,"geo_altitude":11140,"on_ground":false,"velocity":248.7,"true_track":352.27,"vertical_rate":0,"squawk":"1322","aircraft_type":"A333","aircraft_desc":"AIRBUS A-330-300","registration":"VH-QPB"},{"icao24":"7c6a8c","callsign":"VOZ1007","origin_country":"VH-VBY","longitude":148.966713,"latitude":-36.26532,"baro_altitude":12184,"geo_altitude":12520,"on_ground":false,"velocity":230.4,"true_track":10.81,"vertical_rate":0.65,"squawk":"1375","aircraft_type":"B737","aircraft_desc":"BOEING 737-700","registration":"VH-VBY"},{"icao24":"7c78ab","callsign":"QLK6200","origin_country":"VH-X4D","longitude":149.191575,"latitude":-35.311932,"baro_altitude":0,"geo_altitude":null,"on_ground":true,"velocity":0,"true_track":null,"vertical_rate":null,"squawk":"3000","aircraft_type":"BCS3","aircraft_desc":"AIRBUS A220-300","registration":"VH-X4D"},{"icao24":"7c6d33","callsign":"VOZ358","origin_country":"VH-VUT","longitude":149.573364,"latitude":-31.933718,"baro_altitude":11582,"geo_altitude":12146,"on_ground":false,"velocity":193.1,"true_track":217.21,"vertical_rate":0,"squawk":"1127","aircraft_type":"B738","aircraft_desc":"BOEING 737-800","registration":"VH-VUT"},{"icao24":"780ac8","callsign":"CPA138","origin_country":"B-LRS","longitude":149.715325,"latitude":-31.388443,"baro_altitude":10759,"geo_altitude":11308,"on_ground":false,"velocity":242.5,"true_track":343.49,"vertical_rate":5.2,"squawk":"1517","aircraft_type":"A359","aircraft_desc":"AIRBUS A-350-900","registration":"B-LRS"},{"icao24":"7c5c68","callsign":"QFA7411","origin_country":"VH-SJE","longitude":149.733395,"latitude":-34.670929,"baro_altitude":7193,"geo_altitude":7498,"on_ground":false,"velocity":204.9,"true_track":55.95,"vertical_rate":-12.03,"squawk":"4237","aircraft_type":"B463","aircraft_desc":"BRITISH AEROSPACE 146-300","registration":"VH-SJE"},{"icao24":"7c3631","callsign":"KZN","origin_country":"VH-KZN","longitude":150.014359,"latitude":-30.60358,"baro_altitude":1646,"geo_altitude":1768,"on_ground":false,"velocity":80.4,"true_track":150.48,"vertical_rate":0,"squawk":"1200","aircraft_type":"PA44","aircraft_desc":"PIPER PA-44 Seminole","registration":"VH-KZN"},{"icao24":"7c7c9b","callsign":"VOZ1228","origin_country":"VH-YWD","longitude":150.118961,"latitude":-34.91227,"baro_altitude":7041,"geo_altitude":7361,"on_ground":false,"velocity":199.2,"true_track":222.38,"vertical_rate":-12.35,"squawk":"1036","aircraft_type":"B738","aircraft_desc":"BOEING 737-800","registration":"VH-YWD"},{"icao24":"7c0601","callsign":"BGZ","origin_country":"VH-BGZ","longitude":150.464658,"latitude":-33.543137,"baro_altitude":2164,"geo_altitude":2278,"on_ground":false,"velocity":100.5,"true_track":102.12,"vertical_rate":null,"squawk":"4231","aircraft_type":"BE55","aircraft_desc":"BEECH 55 Baron","registration":"VH-BGZ"},{"icao24":"89900f","callsign":"CAL052","origin_country":"B-18902","longitude":150.498738,"latitude":-33.343273,"baro_altitude":5822,"geo_altitude":6111,"on_ground":false,"velocity":196,"true_track":323.43,"vertical_rate":8.78,"squawk":"1567","aircraft_type":"A359","aircraft_desc":"AIRBUS A-350-900","registration":"B-18902"},{"icao24":"7c47a8","callsign":"JST526","origin_country":"VH-OFU","longitude":150.532722,"latitude":-34.234376,"baro_altitude":3071,"geo_altitude":3246,"on_ground":false,"velocity":164.6,"true_track":61.83,"vertical_rate":-3.58,"squawk":"4323","aircraft_type":"A21N","aircraft_desc":"AIRBUS A-321neo","registration":"VH-OFU"},{"icao24":"750563","callsign":"MAS140","origin_country":"9M-MNG","longitude":150.540722,"latitude":-33.751602,"baro_altitude":3543,"geo_altitude":3741,"on_ground":false,"velocity":184.7,"true_track":281.4,"vertical_rate":9.75,"squawk":"1530","aircraft_type":"A339","aircraft_desc":"AIRBUS A-330-900","registration":"9M-MNG"},{"icao24":"7cf7cc","callsign":"SSM3","origin_country":"SSM3","longitude":150.617072,"latitude":-33.546218,"baro_altitude":0,"geo_altitude":null,"on_ground":true,"velocity":null,"true_track":null,"vertical_rate":null,"squawk":"7727","aircraft_type":"TWR","aircraft_desc":null,"registration":"SSM3"},{"icao24":"7c4a79","callsign":"SH161","origin_country":"VH-OZV","longitude":150.662384,"latitude":-23.865967,"baro_altitude":5784,"geo_altitude":6218,"on_ground":false,"velocity":123.8,"true_track":152.26,"vertical_rate":null,"squawk":"6023","aircraft_type":"SW4","aircraft_desc":"SWEARINGEN Metro","registration":"VH-OZV"},{"icao24":"7c01c0","callsign":"AM280","origin_country":"VH-AMQ","longitude":150.837039,"latitude":-31.07121,"baro_altitude":0,"geo_altitude":null,"on_ground":true,"velocity":3,"true_track":null,"vertical_rate":null,"squawk":"2521","aircraft_type":"B350","aircraft_desc":"BEECHCRAFT Super King Air 350","registration":"VH-AMQ"},{"icao24":"7c01c2","callsign":"AM271","origin_country":"VH-AMS","longitude":150.89035,"latitude":-31.279333,"baro_altitude":2995,"geo_altitude":3193,"on_ground":false,"velocity":103.8,"true_track":166.24,"vertical_rate":6.01,"squawk":"1045","aircraft_type":"B350","aircraft_desc":"BEECHCRAFT Super King Air 350","registration":"VH-AMS"},{"icao24":"7c045e","callsign":"JST224","origin_country":"VH-A5C","longitude":151.163406,"latitude":-33.938804,"baro_altitude":0,"geo_altitude":null,"on_ground":true,"velocity":4.2,"true_track":null,"vertical_rate":null,"squawk":"0275","aircraft_type":"A20N","aircraft_desc":"AIRBUS A-320neo","registration":"VH-A5C"},{"icao24":"7c5be9","callsign":"QFA7293","origin_country":"VH-SFV","longitude":151.168091,"latitude":-33.930977,"baro_altitude":0,"geo_altitude":null,"on_ground":true,"velocity":0,"true_track":null,"vertical_rate":null,"squawk":"3674","aircraft_type":"B462","aircraft_desc":"BRITISH AEROSPACE 146-200 Quiet Trader","registration":"VH-SFV"},{"icao24":"7cf07c","callsign":"CAR28","origin_country":"CAR 28","longitude":151.168498,"latitude":-33.931183,"baro_altitude":0,"geo_altitude":null,"on_ground":true,"velocity":1.4,"true_track":165.94,"vertical_rate":null,"squawk":null,"aircraft_type":"SERV","aircraft_desc":"Ground Vehicle","registration":"CAR 28"},{"icao24":"7c5d71","callsign":"QFA7226","origin_country":"VH-SQR","longitude":151.170831,"latitude":-33.934079,"baro_altitude":0,"geo_altitude":null,"on_ground":true,"velocity":6.1,"true_track":null,"vertical_rate":null,"squawk":"1226","aircraft_type":"B463","aircraft_desc":"BRITISH AEROSPACE 146-300","registration":"VH-SQR"},{"icao24":"7cf452","callsign":"","origin_country":"","longitude":151.173851,"latitude":-33.928471,"baro_altitude":0,"geo_altitude":null,"on_ground":true,"velocity":4.2,"true_track":337.5,"vertical_rate":null,"squawk":null,"aircraft_type":null,"aircraft_desc":null,"registration":null},{"icao24":"7811a4","callsign":"CCA174","origin_country":"B-1468","longitude":151.174453,"latitude":-33.948166,"baro_altitude":0,"geo_altitude":null,"on_ground":true,"velocity":11.6,"true_track":168,"vertical_rate":0,"squawk":"1360","aircraft_type":"B789","aircraft_desc":"BOEING 787-9 Dreamliner","registration":"B-1468"},{"icao24":"7cf4a6","callsign":"RED O","origin_country":"","longitude":151.176624,"latitude":-33.931786,"baro_altitude":0,"geo_altitude":null,"on_ground":true,"velocity":0,"true_track":null,"vertical_rate":null,"squawk":null,"aircraft_type":null,"aircraft_desc":null,"registration":null},{"icao24":"7c47ba","callsign":"QFA498","origin_country":"VH-OGC","longitude":151.176696,"latitude":-33.941162,"baro_altitude":0,"geo_altitude":null,"on_ground":true,"velocity":9,"true_track":null,"vertical_rate":0,"squawk":"4207","aircraft_type":"A21N","aircraft_desc":"AIRBUS A-321neo","registration":"VH-OGC"},{"icao24":"7c78af","callsign":"QLK1581","origin_country":"VH-X4H","longitude":151.177654,"latitude":-33.944216,"baro_altitude":0,"geo_altitude":null,"on_ground":true,"velocity":5.2,"true_track":330,"vertical_rate":-0.33,"squawk":"1215","aircraft_type":"BCS3","aircraft_desc":"AIRBUS A220-300","registration":"VH-X4H"},{"icao24":"7c7543","callsign":"QFA7340","origin_country":"VH-XF5","longitude":151.178484,"latitude":-33.941818,"baro_altitude":0,"geo_altitude":null,"on_ground":true,"velocity":13.1,"true_track":null,"vertical_rate":0,"squawk":"1251","aircraft_type":"A321","aircraft_desc":"AIRBUS A-321","registration":"VH-XF5"},{"icao24":"769104","callsign":"SIA7439","origin_country":"9V-DHD","longitude":151.179204,"latitude":-33.964382,"baro_altitude":0,"geo_altitude":null,"on_ground":true,"velocity":0.1,"true_track":19,"vertical_rate":0,"squawk":"1564","aircraft_type":"B77L","aircraft_desc":"BOEING 777-200LR","registration":"9V-DHD"},{"icao24":"7c7887","callsign":"JST821","origin_country":"VH-X3D","longitude":151.17954,"latitude":-33.951347,"baro_altitude":0,"geo_altitude":null,"on_ground":true,"velocity":5.8,"true_track":345.94,"vertical_rate":0,"squawk":"1137","aircraft_type":"A320","aircraft_desc":"AIRBUS A-320","registration":"VH-X3D"},{"icao24":"7cf4d3","callsign":"CAR85","origin_country":"","longitude":151.181726,"latitude":-33.935715,"baro_altitude":0,"geo_altitude":null,"on_ground":true,"velocity":0,"true_track":null,"vertical_rate":null,"squawk":null,"aircraft_type":null,"aircraft_desc":null,"registration":null},{"icao24":"~7cf44d","callsign":"CAR70","origin_country":"","longitude":151.181874,"latitude":-33.935569,"baro_altitude":0,"geo_altitude":null,"on_ground":true,"velocity":1.6,"true_track":84.38,"vertical_rate":null,"squawk":null,"aircraft_type":null,"aircraft_desc":null,"registration":null},{"icao24":"c82ae4","callsign":"TFX41","origin_country":"ZK-TXC","longitude":151.182089,"latitude":-33.950838,"baro_altitude":0,"geo_altitude":null,"on_ground":true,"velocity":8,"true_track":84,"vertical_rate":0,"squawk":"1334","aircraft_type":"B738","aircraft_desc":"BOEING 737-800","registration":"ZK-TXC"},{"icao24":"7c7c74","callsign":"VOZ1537","origin_country":"VH-YVA","longitude":151.182637,"latitude":-33.972061,"baro_altitude":53,"geo_altitude":84,"on_ground":false,"velocity":73.2,"true_track":347.82,"vertical_rate":-4.88,"squawk":"4353","aircraft_type":"B738","aircraft_desc":"BOEING 737-800","registration":"VH-YVA"},{"icao24":"7c1468","callsign":"QFA7345","origin_country":"VH-EBE","longitude":151.187808,"latitude":-33.955433,"baro_altitude":0,"geo_altitude":null,"on_ground":true,"velocity":12.1,"true_track":180,"vertical_rate":0,"squawk":"4356","aircraft_type":"A332","aircraft_desc":"AIRBUS A-330-200","registration":"VH-EBE"},{"icao24":"7c6d7c","callsign":"JST987","origin_country":"VH-VWU","longitude":151.209094,"latitude":-34.073822,"baro_altitude":610,"geo_altitude":648,"on_ground":false,"velocity":82.1,"true_track":348.06,"vertical_rate":0.16,"squawk":"3746","aircraft_type":"A321","aircraft_desc":"AIRBUS A-321","registration":"VH-VWU"},{"icao24":"7cf7cb","callsign":"SSM2","origin_country":"SSM2","longitude":151.209715,"latitude":-33.87261,"baro_altitude":0,"geo_altitude":null,"on_ground":true,"velocity":9.3,"true_track":180,"vertical_rate":null,"squawk":"7722","aircraft_type":"TWR","aircraft_desc":null,"registration":"SSM2"},{"icao24":"7cf7ca","callsign":"SSM1","origin_country":"SSM1","longitude":151.21134,"latitude":-33.873024,"baro_altitude":0,"geo_altitude":null,"on_ground":true,"velocity":5.1,"true_track":158,"vertical_rate":null,"squawk":"7712","aircraft_type":"TWR","aircraft_desc":null,"registration":"SSM1"},{"icao24":"7c0d8a","callsign":"PHA71","origin_country":"VH-CYK","longitude":151.468898,"latitude":-33.961853,"baro_altitude":2896,"geo_altitude":3048,"on_ground":false,"velocity":156.2,"true_track":117.24,"vertical_rate":15.93,"squawk":"1501","aircraft_type":"B738","aircraft_desc":"BOEING 737-800","registration":"VH-CYK"},{"icao24":"a21c82","callsign":"N235QS","origin_country":"N235QS","longitude":151.640552,"latitude":-29.979036,"baro_altitude":11270,"geo_altitude":11918,"on_ground":false,"velocity":190.4,"true_track":220.84,"vertical_rate":2.6,"squawk":"1034","aircraft_type":"CL60","aircraft_desc":"BOMBARDIER CL-600 Challenger","registration":"N235QS"},{"icao24":"7c4320","callsign":"JTE7434","origin_country":"VH-NJM","longitude":151.663513,"latitude":-31.2052,"baro_altitude":8534,"geo_altitude":8954,"on_ground":false,"velocity":174.4,"true_track":194.69,"vertical_rate":null,"squawk":"1224","aircraft_type":"B463","aircraft_desc":"BRITISH AEROSPACE 146-300","registration":"VH-NJM"},{"icao24":"7c6db1","callsign":"QFA558","origin_country":"VH-VYB","longitude":151.910431,"latitude":-32.478928,"baro_altitude":9502,"geo_altitude":9975,"on_ground":false,"velocity":260.9,"true_track":18.86,"vertical_rate":4.71,"squawk":"1357","aircraft_type":"B738","aircraft_desc":"BOEING 737-800","registration":"VH-VYB"},{"icao24":"7c7ab5","callsign":"VOZ349","origin_country":"VH-YIV","longitude":152.50946,"latitude":-29.447782,"baro_altitude":11079,"geo_altitude":11727,"on_ground":false,"velocity":270.8,"true_track":38.13,"vertical_rate":-5.69,"squawk":"1554","aircraft_type":"B738","aircraft_desc":"BOEING 737-800","registration":"VH-YIV"},{"icao24":"7c71d7","callsign":"WRT","origin_country":"VH-WRT","longitude":152.787135,"latitude":-28.040973,"baro_altitude":2362,"geo_altitude":2537,"on_ground":false,"velocity":109.3,"true_track":6.49,"vertical_rate":-2.93,"squawk":"1362","aircraft_type":"BE58","aircraft_desc":"BEECH 58 Baron","registration":"VH-WRT"},{"icao24":"7cad44","callsign":"VOZ050","origin_country":"VH-8IE","longitude":152.875015,"latitude":-27.41748,"baro_altitude":1821,"geo_altitude":1981,"on_ground":false,"velocity":138.6,"true_track":158.67,"vertical_rate":-1.63,"squawk":"4137","aircraft_type":"B38M","aircraft_desc":"BOEING 737 MAX 8","registration":"VH-8IE"},{"icao24":"7c7599","callsign":"RSCU522","origin_country":"VH-XIJ","longitude":152.949125,"latitude":-26.294938,"baro_altitude":1798,"geo_altitude":1966,"on_ground":false,"velocity":88.6,"true_track":338.2,"vertical_rate":0.33,"squawk":"4416","aircraft_type":"A139","aircraft_desc":"AGUSTA AW-139","registration":"VH-XIJ"},{"icao24":"7c66e4","callsign":"QFA7335","origin_country":"VH-ULY","longitude":153.108656,"latitude":-27.407261,"baro_altitude":0,"geo_altitude":null,"on_ground":true,"velocity":0,"true_track":59.06,"vertical_rate":null,"squawk":"1176","aircraft_type":"A321","aircraft_desc":"AIRBUS A-321","registration":"VH-ULY"},{"icao24":"7c4dcc","callsign":"RON41","origin_country":"VH-PNI","longitude":153.116157,"latitude":-27.402924,"baro_altitude":0,"geo_altitude":null,"on_ground":true,"velocity":null,"true_track":null,"vertical_rate":null,"squawk":null,"aircraft_type":"B733","aircraft_desc":"BOEING 737-300","registration":"VH-PNI"},{"icao24":"7c7cce","callsign":"JST634","origin_country":"VH-YXS","longitude":153.122529,"latitude":-27.386088,"baro_altitude":0,"geo_altitude":null,"on_ground":true,"velocity":1.6,"true_track":292.5,"vertical_rate":null,"squawk":"1265","aircraft_type":"A320","aircraft_desc":"AIRBUS A-320","registration":"VH-YXS"},{"icao24":"7c39f3","callsign":"VH-LQD","origin_country":"VH-LQD","longitude":153.128698,"latitude":-27.378971,"baro_altitude":0,"geo_altitude":null,"on_ground":true,"velocity":6.1,"true_track":null,"vertical_rate":null,"squawk":"3000","aircraft_type":"DH8D","aircraft_desc":"DE HAVILLAND DHC-8-400 Dash 8","registration":"VH-LQD"},{"icao24":"7c19c4","callsign":"FD467","origin_country":"VH-FDI","longitude":153.160141,"latitude":-27.329453,"baro_altitude":1006,"geo_altitude":1128,"on_ground":false,"velocity":71.6,"true_track":27.85,"vertical_rate":7.32,"squawk":"6007","aircraft_type":"BE20","aircraft_desc":"BEECH 200 Super King Air","registration":"VH-FDI"},{"icao24":"899088","callsign":"EVA316","origin_country":"B-17801","longitude":153.203712,"latitude":-26.5682,"baro_altitude":5220,"geo_altitude":5555,"on_ground":false,"velocity":187.6,"true_track":342.61,"vertical_rate":3.9,"squawk":"1006","aircraft_type":"B78X","aircraft_desc":"BOEING 787-10 Dreamliner","registration":"B-17801"},{"icao24":"7c0184","callsign":"QFA7494","origin_country":"VH-AK2","longitude":153.211899,"latitude":-27.583597,"baro_altitude":2667,"geo_altitude":2850,"on_ground":false,"velocity":90.8,"true_track":203.37,"vertical_rate":4.88,"squawk":"1061","aircraft_type":"AT72","aircraft_desc":"ATR-72-202","registration":"VH-AK2"},{"icao24":"7c7542","callsign":"QFA7523","origin_country":"VH-XF4","longitude":153.221283,"latitude":-34.485712,"baro_altitude":8687,"geo_altitude":9030,"on_ground":false,"velocity":252.6,"true_track":110.5,"vertical_rate":5.2,"squawk":"1532","aircraft_type":"A321","aircraft_desc":"AIRBUS A-321","registration":"VH-XF4"},{"icao24":"781f73","callsign":"CSN306","origin_country":"B-32ED","longitude":153.580109,"latitude":-23.962392,"baro_altitude":11430,"geo_altitude":12184,"on_ground":false,"velocity":241.4,"true_track":309.12,"vertical_rate":0,"squawk":"0201","aircraft_type":"A359","aircraft_desc":"AIRBUS A-350-900","registration":"B-32ED"},{"icao24":"7c6de9","callsign":"QFA184","origin_country":"VH-VZV","longitude":153.804263,"latitude":-27.477645,"baro_altitude":4054,"geo_altitude":4328,"on_ground":false,"velocity":192.5,"true_track":280.47,"vertical_rate":-13,"squawk":"6066","aircraft_type":"B738","aircraft_desc":"BOEING 737-800","registration":"VH-VZV"},{"icao24":"780fd9","callsign":"CA784","origin_country":"B-7877","longitude":156.888714,"latitude":-4.376163,"baro_altitude":10972,"geo_altitude":null,"on_ground":false,"velocity":257.7,"true_track":328,"vertical_rate":0,"squawk":"0010","aircraft_type":"B789","aircraft_desc":"BOEING 787-9 Dreamliner","registration":"B-7877"},{"icao24":"780f3a","callsign":"MU780","origin_country":"B-7347","longitude":162.539463,"latitude":-14.921837,"baro_altitude":9144,"geo_altitude":null,"on_ground":false,"velocity":null,"true_track":332.55,"vertical_rate":null,"squawk":"0010","aircraft_type":"B77W","aircraft_desc":"BOEING 777-300ER","registration":"B-7347"},{"icao24":"7c806e","callsign":"QF75","origin_country":"VH-ZNK","longitude":163.005695,"latitude":-24.49419,"baro_altitude":10667,"geo_altitude":null,"on_ground":false,"velocity":302,"true_track":42.35,"vertical_rate":0,"squawk":"0010","aircraft_type":"B789","aircraft_desc":"BOEING 787-9 Dreamliner","registration":"VH-ZNK"},{"icao24":"c87ed7","callsign":"TWR","origin_country":"TWR","longitude":167.833208,"latitude":-46.168519,"baro_altitude":0,"geo_altitude":null,"on_ground":true,"velocity":null,"true_track":null,"vertical_rate":null,"squawk":null,"aircraft_type":"TWR","aircraft_desc":null,"registration":"TWR"},{"icao24":"c87ed8","callsign":"","origin_country":"","longitude":169.770218,"latitude":-46.075892,"baro_altitude":0,"geo_altitude":null,"on_ground":true,"velocity":null,"true_track":null,"vertical_rate":null,"squawk":null,"aircraft_type":null,"aircraft_desc":null,"registration":null},{"icao24":"c87ed6","callsign":"TWR","origin_country":"TWR","longitude":170.554354,"latitude":-45.813274,"baro_altitude":0,"geo_altitude":null,"on_ground":true,"velocity":null,"true_track":null,"vertical_rate":null,"squawk":null,"aircraft_type":"TWR","aircraft_desc":null,"registration":"TWR"},{"icao24":"c87ed5","callsign":"TWR","origin_country":"TWR","longitude":170.910622,"latitude":-44.641478,"baro_altitude":0,"geo_altitude":null,"on_ground":true,"velocity":null,"true_track":null,"vertical_rate":null,"squawk":null,"aircraft_type":"TWR","aircraft_desc":null,"registration":"TWR"},{"icao24":"7c7803","callsign":"QFA135","origin_country":"VH-XZP","longitude":171.032535,"latitude":-42.570694,"baro_altitude":8679,"geo_altitude":8824,"on_ground":false,"velocity":229.5,"true_track":140.64,"vertical_rate":-18.04,"squawk":"1071","aircraft_type":"B738","aircraft_desc":"BOEING 737-800","registration":"VH-XZP"},{"icao24":"c82396","callsign":"AWK76","origin_country":"ZK-PAT","longitude":172.428981,"latitude":-43.506511,"baro_altitude":1006,"geo_altitude":1044,"on_ground":false,"velocity":125,"true_track":332.8,"vertical_rate":10.73,"squawk":"5242","aircraft_type":"B734","aircraft_desc":"BOEING 737-400","registration":"ZK-PAT"},{"icao24":"c82744","callsign":"ANZ204","origin_country":"ZK-NNA","longitude":172.539804,"latitude":-43.486542,"baro_altitude":0,"geo_altitude":null,"on_ground":true,"velocity":1.6,"true_track":null,"vertical_rate":null,"squawk":"1020","aircraft_type":"A21N","aircraft_desc":"AIRBUS A-321neo","registration":"ZK-NNA"},{"icao24":"c81d80","callsign":"ANZ282","origin_country":"ZK-OKN","longitude":173.219318,"latitude":-36.778427,"baro_altitude":9754,"geo_altitude":10127,"on_ground":false,"velocity":230.2,"true_track":280.43,"vertical_rate":0.33,"squawk":"0206","aircraft_type":"B77W","aircraft_desc":"BOEING 777-300ER","registration":"ZK-OKN"},{"icao24":"7c1471","callsign":"QFA149","origin_country":"VH-EBN","longitude":173.622787,"latitude":-37.138779,"baro_altitude":4115,"geo_altitude":4321,"on_ground":false,"velocity":182.7,"true_track":85.48,"vertical_rate":-9.43,"squawk":"1306","aircraft_type":"A332","aircraft_desc":"AIRBUS A-330-200","registration":"VH-EBN"},{"icao24":"c8277f","callsign":"NOR7","origin_country":"ZK-HQO","longitude":174.377688,"latitude":-35.917426,"baro_altitude":1204,"geo_altitude":1311,"on_ground":false,"velocity":67.7,"true_track":150.9,"vertical_rate":0,"squawk":"5772","aircraft_type":"S76","aircraft_desc":"SIKORSKY S-76 Spirit","registration":"ZK-HQO"},{"icao24":"c827ee","callsign":"ANZ999","origin_country":"ZK-NNF","longitude":174.441396,"latitude":-36.947161,"baro_altitude":1722,"geo_altitude":1829,"on_ground":false,"velocity":144.3,"true_track":170.97,"vertical_rate":-7.48,"squawk":"4412","aircraft_type":"A21N","aircraft_desc":"AIRBUS A-321neo","registration":"ZK-NNF"},{"icao24":"7c788f","callsign":"JST114","origin_country":"VH-X3L","longitude":174.549179,"latitude":-36.733017,"baro_altitude":3002,"geo_altitude":3162,"on_ground":false,"velocity":154.6,"true_track":206.91,"vertical_rate":-7.15,"squawk":"4404","aircraft_type":"A320","aircraft_desc":"AIRBUS A-320","registration":"VH-X3L"},{"icao24":"c8274f","callsign":"@@@@@@@@","origin_country":"ZK-NNB","longitude":174.777061,"latitude":-37.006201,"baro_altitude":0,"geo_altitude":null,"on_ground":true,"velocity":0.6,"true_track":null,"vertical_rate":null,"squawk":null,"aircraft_type":"A21N","aircraft_desc":"AIRBUS A-321neo","registration":"ZK-NNB"},{"icao24":"7505bc","callsign":"MAS132","origin_country":"","longitude":174.783644,"latitude":-37.008936,"baro_altitude":0,"geo_altitude":null,"on_ground":true,"velocity":0,"true_track":null,"vertical_rate":null,"squawk":"0207","aircraft_type":null,"aircraft_desc":null,"registration":null},{"icao24":"c82b32","callsign":"ANZ949","origin_country":"ZK-NNI","longitude":174.784256,"latitude":-37.01067,"baro_altitude":0,"geo_altitude":null,"on_ground":true,"velocity":8.5,"true_track":null,"vertical_rate":null,"squawk":"4406","aircraft_type":"A21N","aircraft_desc":"AIRBUS A-321neo","registration":"ZK-NNI"},{"icao24":"c87ee1","callsign":"TXLU00","origin_country":"TWR","longitude":174.78893,"latitude":-37.006313,"baro_altitude":0,"geo_altitude":null,"on_ground":true,"velocity":null,"true_track":null,"vertical_rate":null,"squawk":null,"aircraft_type":"TWR","aircraft_desc":null,"registration":"TWR"},{"icao24":"c87e7b","callsign":"AP57","origin_country":"","longitude":174.797168,"latitude":-37.008051,"baro_altitude":0,"geo_altitude":null,"on_ground":true,"velocity":null,"true_track":null,"vertical_rate":null,"squawk":null,"aircraft_type":null,"aircraft_desc":null,"registration":null},{"icao24":"c87ee2","callsign":"TXLU01","origin_country":"TWR","longitude":174.804402,"latitude":-37.01524,"baro_altitude":0,"geo_altitude":null,"on_ground":true,"velocity":null,"true_track":null,"vertical_rate":null,"squawk":null,"aircraft_type":"TWR","aircraft_desc":null,"registration":"TWR"},{"icao24":"c87ec2","callsign":"APT1","origin_country":"","longitude":174.807836,"latitude":-41.331335,"baro_altitude":0,"geo_altitude":null,"on_ground":true,"velocity":3.7,"true_track":104.06,"vertical_rate":null,"squawk":null,"aircraft_type":null,"aircraft_desc":null,"registration":null},{"icao24":"c827a6","callsign":"ANZ248","origin_country":"ZK-NHB","longitude":174.810196,"latitude":-41.327682,"baro_altitude":0,"geo_altitude":null,"on_ground":true,"velocity":0,"true_track":null,"vertical_rate":null,"squawk":"2000","aircraft_type":"A20N","aircraft_desc":"AIRBUS A-320neo","registration":"ZK-NHB"},{"icao24":"c83311","callsign":"NOR4","origin_country":"ZK-IRB","longitude":175.11909,"latitude":-36.738095,"baro_altitude":2111,"geo_altitude":2248,"on_ground":false,"velocity":70.7,"true_track":13.03,"vertical_rate":null,"squawk":"5241","aircraft_type":"A169","aircraft_desc":"AGUSTA AW-169","registration":"ZK-IRB"},{"icao24":"c87ef1","callsign":"","origin_country":"","longitude":178.32083,"latitude":-38.16861,"baro_altitude":0,"geo_altitude":null,"on_ground":true,"velocity":0,"true_track":165.94,"vertical_rate":null,"squawk":"0005","aircraft_type":null,"aircraft_desc":null,"registration":null},{"icao24":"c87efd","callsign":"TXP1HAWK","origin_country":"","longitude":179.024714,"latitude":-41.584442,"baro_altitude":0,"geo_altitude":null,"on_ground":true,"velocity":0,"true_track":165.94,"vertical_rate":null,"squawk":"0041","aircraft_type":null,"aircraft_desc":null,"registration":null},{"icao24":"c87efe","callsign":"TXP2HAWK","origin_country":"","longitude":179.691121,"latitude":-41.609985,"baro_altitude":0,"geo_altitude":null,"on_ground":true,"velocity":0,"true_track":165.94,"vertical_rate":null,"squawk":"0047","aircraft_type":null,"aircraft_desc":null,"registration":null}],"_source":"airplanes.live","_collected_at":"2026-04-09T12:36:42.936Z"}